fapilog/__init__.py
fapilog/_version.py
fapilog/builder.py
fapilog/py.typed
fapilog/caching/__init__.py
fapilog/caching/cache.py
fapilog/cli/__init__.py
fapilog/cli/main.py
fapilog/containers/__init__.py
fapilog/containers/container.py
fapilog/containers/lifecycle.py
fapilog/core/__init__.py
fapilog/core/access_control.py
fapilog/core/adaptive.py
fapilog/core/advanced_validation.py
fapilog/core/change_detection.py
fapilog/core/circuit_breaker.py
fapilog/core/concurrency.py
fapilog/core/config.py
fapilog/core/config_builders.py
fapilog/core/context.py
fapilog/core/defaults.py
fapilog/core/diagnostics.py
fapilog/core/encryption.py
fapilog/core/envelope.py
fapilog/core/environment.py
fapilog/core/errors.py
fapilog/core/events.py
fapilog/core/hot_reload.py
fapilog/core/lifecycle.py
fapilog/core/logger.py
fapilog/core/migration.py
fapilog/core/observability.py
fapilog/core/plugin_config.py
fapilog/core/presets.py
fapilog/core/processing.py
fapilog/core/resources.py
fapilog/core/retry.py
fapilog/core/routing.py
fapilog/core/schema.py
fapilog/core/security.py
fapilog/core/serialization.py
fapilog/core/settings.py
fapilog/core/shutdown.py
fapilog/core/sink_writers.py
fapilog/core/stdlib_bridge.py
fapilog/core/types.py
fapilog/core/validation.py
fapilog/core/worker.py
fapilog/fastapi/__init__.py
fapilog/fastapi/context.py
fapilog/fastapi/dependencies.py
fapilog/fastapi/integration.py
fapilog/fastapi/logging.py
fapilog/fastapi/setup.py
fapilog/metrics/__init__.py
fapilog/metrics/metrics.py
fapilog/plugins/__init__.py
fapilog/plugins/health.py
fapilog/plugins/loader.py
fapilog/plugins/metadata.py
fapilog/plugins/utils.py
fapilog/plugins/versioning.py
fapilog/plugins/enrichers/__init__.py
fapilog/plugins/enrichers/context_vars.py
fapilog/plugins/enrichers/kubernetes.py
fapilog/plugins/enrichers/runtime_info.py
fapilog/plugins/filters/__init__.py
fapilog/plugins/filters/adaptive_sampling.py
fapilog/plugins/filters/first_occurrence.py
fapilog/plugins/filters/level.py
fapilog-0.12.0.dist-info/METADATA
fapilog-0.12.0.dist-info/WHEEL
fapilog-0.12.0.dist-info/licenses/LICENSE
fapilog-0.12.0.dist-info/RECORD
