Metadata-Version: 2.4
Name: fapilog
Version: 0.12.0
Summary: Async-first structured logging for Python services
Project-URL: Homepage, https://fapilog.dev
Project-URL: Documentation, https://fapilog.readthedocs.io/en/stable/
Project-URL: Repository, https://github.com/chris-haste/fapilog
Project-URL: Bug Tracker, https://github.com/chris-haste/fapilog/issues
Project-URL: Discord, https://discord.gg/gHaNsczWte
Project-URL: Changelog, https://github.com/chris-haste/fapilog/blob/main/CHANGELOG.md
Author-email: Chris Haste <dev@fapilog.dev>
Maintainer-email: Chris Haste <dev@fapilog.dev>
License-Expression: Apache-2.0
License-File: LICENSE
Keywords: async,enterprise,fastapi,logging,observability
Classifier: Development Status :: 4 - Beta
Classifier: Framework :: FastAPI
Classifier: Intended Audience :: Developers
Classifier: License :: OSI Approved :: Apache Software License
Classifier: Operating System :: OS Independent
Classifier: Programming Language :: Python :: 3
Classifier: Programming Language :: Python :: 3.10
Classifier: Programming Language :: Python :: 3.11
Classifier: Programming Language :: Python :: 3.12
Classifier: Programming Language :: Python :: 3.13
Classifier: Programming Language :: Python :: 3.14
Classifier: Topic :: Software Development :: Libraries :: Python Modules
Classifier: Topic :: System :: Logging
Classifier: Typing :: Typed
Requires-Python: >=3.10
Requires-Dist: httpx>=0.24.0
Requires-Dist: orjson>=3.9.15
Requires-Dist: packaging>=23.0
Requires-Dist: pydantic-settings>=2.0.0
Requires-Dist: pydantic>=2.11.0
Provides-Extra: all
Requires-Dist: asyncio-mqtt>=0.16.0; extra == 'all'
Requires-Dist: asyncpg>=0.28.0; extra == 'all'
Requires-Dist: black>=23.0.0; extra == 'all'
Requires-Dist: boto3>=1.26.0; extra == 'all'
Requires-Dist: diff-cover>=9.0.0; extra == 'all'
Requires-Dist: fastapi>=0.115.0; extra == 'all'
Requires-Dist: hatch>=1.7.0; extra == 'all'
Requires-Dist: httpx>=0.24.0; extra == 'all'
Requires-Dist: hypothesis>=6.100.0; extra == 'all'
Requires-Dist: isort>=5.12.0; extra == 'all'
Requires-Dist: jsonschema>=4.0.0; extra == 'all'
Requires-Dist: mypy>=1.17.1; extra == 'all'
Requires-Dist: myst-parser>=1.0.0; extra == 'all'
Requires-Dist: pre-commit>=3.3.0; extra == 'all'
Requires-Dist: prometheus-client>=0.17.0; extra == 'all'
Requires-Dist: psutil>=5.9.0; (sys_platform != 'win32') and extra == 'all'
Requires-Dist: pytest-asyncio>=1.1.0; extra == 'all'
Requires-Dist: pytest-benchmark>=4.0.0; extra == 'all'
Requires-Dist: pytest-cov>=6.2.0; extra == 'all'
Requires-Dist: pytest>=8.4.0; extra == 'all'
Requires-Dist: ruff>=0.12.0; extra == 'all'
Requires-Dist: sphinx-autodoc-typehints>=1.24.0; extra == 'all'
Requires-Dist: sphinx-copybutton>=0.5.0; extra == 'all'
Requires-Dist: sphinx-rtd-theme>=1.3.0; extra == 'all'
Requires-Dist: sphinx>=6.0.0; extra == 'all'
Requires-Dist: sphinxcontrib-mermaid>=0.9.0; extra == 'all'
Requires-Dist: vulture>=2.9.0; extra == 'all'
Provides-Extra: aws
Requires-Dist: boto3>=1.26.0; extra == 'aws'
Provides-Extra: dev
Requires-Dist: black>=23.0.0; extra == 'dev'
Requires-Dist: diff-cover>=9.0.0; extra == 'dev'
Requires-Dist: hatch>=1.7.0; extra == 'dev'
Requires-Dist: hypothesis>=6.100.0; extra == 'dev'
Requires-Dist: isort>=5.12.0; extra == 'dev'
Requires-Dist: jsonschema>=4.0.0; extra == 'dev'
Requires-Dist: mypy>=1.17.1; extra == 'dev'
Requires-Dist: pre-commit>=3.3.0; extra == 'dev'
Requires-Dist: pytest-asyncio>=1.1.0; extra == 'dev'
Requires-Dist: pytest-benchmark>=4.0.0; extra == 'dev'
Requires-Dist: pytest-cov>=6.2.0; extra == 'dev'
Requires-Dist: pytest>=8.4.0; extra == 'dev'
Requires-Dist: ruff>=0.12.0; extra == 'dev'
Requires-Dist: vulture>=2.9.0; extra == 'dev'
Provides-Extra: docs
Requires-Dist: myst-parser>=1.0.0; extra == 'docs'
Requires-Dist: sphinx-autodoc-typehints>=1.24.0; extra == 'docs'
Requires-Dist: sphinx-copybutton>=0.5.0; extra == 'docs'
Requires-Dist: sphinx-rtd-theme>=1.3.0; extra == 'docs'
Requires-Dist: sphinx>=6.0.0; extra == 'docs'
Requires-Dist: sphinxcontrib-mermaid>=0.9.0; extra == 'docs'
Provides-Extra: fastapi
Requires-Dist: fastapi>=0.115.0; extra == 'fastapi'
Provides-Extra: http
Requires-Dist: httpx>=0.24.0; extra == 'http'
Provides-Extra: metrics
Requires-Dist: prometheus-client>=0.17.0; extra == 'metrics'
Provides-Extra: mqtt
Requires-Dist: asyncio-mqtt>=0.16.0; extra == 'mqtt'
Provides-Extra: postgres
Requires-Dist: asyncpg>=0.28.0; extra == 'postgres'
Provides-Extra: system
Requires-Dist: psutil>=5.9.0; (sys_platform != 'win32') and extra == 'system'
